.gitignore
MANIFEST.in
setup.py
ebs/__init__.py
ebs/signagenode/__init__.py
ebs/signagenode/app.py
ebs/signagenode/node.py
ebs/signagenode/fonts/FreeSans.ttf
ebs/signagenode/fonts/Sakalbharati.ttf
ebs/signagenode/fonts/noto/NotoSans-Bold.ttf
ebs/signagenode/fonts/noto/NotoSans-Italic.ttf
ebs/signagenode/fonts/noto/NotoSans-Regular.ttf
ebs/signagenode/fonts/noto/NotoSansArabic-Bold.ttf
ebs/signagenode/fonts/noto/NotoSansArabic-Regular.ttf
ebs/signagenode/fonts/noto/NotoSansBengali-Bold.ttf
ebs/signagenode/fonts/noto/NotoSansBengali-Regular.ttf
ebs/signagenode/fonts/noto/NotoSansDevanagari-Bold.ttf
ebs/signagenode/fonts/noto/NotoSansDevanagari-Regular.ttf
ebs/signagenode/fonts/noto/NotoSansGujarati-Bold.ttf
ebs/signagenode/fonts/noto/NotoSansGujarati-Regular.ttf
ebs/signagenode/fonts/noto/NotoSansGurmukhi-Bold.ttf
ebs/signagenode/fonts/noto/NotoSansGurmukhi-Regular.ttf
ebs/signagenode/fonts/noto/NotoSansKannada-Bold.ttf
ebs/signagenode/fonts/noto/NotoSansKannada-Regular.ttf
ebs/signagenode/fonts/noto/NotoSansMalayalam-Bold.ttf
ebs/signagenode/fonts/noto/NotoSansMalayalam-Regular.ttf
ebs/signagenode/fonts/noto/NotoSansOriya-Bold.ttf
ebs/signagenode/fonts/noto/NotoSansOriya-Regular.ttf
ebs/signagenode/fonts/noto/NotoSansTamil-Bold.ttf
ebs/signagenode/fonts/noto/NotoSansTamil-Regular.ttf
ebs/signagenode/fonts/noto/NotoSansTelugu-Bold.ttf
ebs/signagenode/fonts/noto/NotoSansTelugu-Regular.ttf
ebs/signagenode/scheduler/__init__.py
ebs/signagenode/scheduler/events.py
ebs/signagenode/scheduler/mixin.py
ebs/signagenode/scheduler/model.py
ebs/signagenode/scheduler/resources.py
ebs/signagenode/scheduler/eventmanagers/__init__.py
ebs/signagenode/scheduler/eventmanagers/base.py
ebs/signagenode/scheduler/eventmanagers/text.py
ebs/signagenode/scheduler/eventmanagers/webresource.py
ebs_signagenode.egg-info/PKG-INFO
ebs_signagenode.egg-info/SOURCES.txt
ebs_signagenode.egg-info/dependency_links.txt
ebs_signagenode.egg-info/requires.txt
ebs_signagenode.egg-info/top_level.txt
example/app.py
example/node.py
example/runnode.py